pyprnt/__init__.py
pyprnt/helper.py
pyprnt/position.py
pyprnt/prnt.py
pyprnt/pyprnt.py
pyprnt/util.py
pyprnt-2.5.3.dist-info/LICENSE
pyprnt-2.5.3.dist-info/METADATA
pyprnt-2.5.3.dist-info/WHEEL
pyprnt-2.5.3.dist-info/top_level.txt
pyprnt-2.5.3.dist-info/RECORD
