Metadata-Version: 2.1
Name: pyprnt
Version: 2.5.3
Summary: A Modern Python Pretty Printer
Home-page: https://github.com/kevink1103/pyprnt
Author: Kevin Kim
Author-email: kevink1103@gmail.com
License: MIT
Download-URL: https://github.com/kevink1103/pyprnt/dist/pyprnt-2.5.3-py3-none-any.whl
Keywords: pretty,print
Platform: UNKNOWN
Classifier: Programming Language :: Python :: 3.3
Classifier: Programming Language :: Python :: 3.4
Classifier: Programming Language :: Python :: 3.5
Classifier: Programming Language :: Python :: 3.6
Classifier: Programming Language :: Python :: 3.7
Classifier: Programming Language :: Python :: 3.8
Requires-Python: >=3.3
